ws_robot/__init__.py
ws_robot/robot_api_body.py
ws_robot/ws_message.py
ws_robot/ws_robot_client.py
ws_robot/ws_robot_instance.py
ws_robot/ws_robot_manager.py
ws_robot/ws_robot_use.py
ws_robot-1.0.2.dist-info/licenses/LICENSE
ws_robot-1.0.2.dist-info/METADATA
ws_robot-1.0.2.dist-info/WHEEL
ws_robot-1.0.2.dist-info/top_level.txt
ws_robot-1.0.2.dist-info/RECORD
